{
  "main": {
    "id": "861294fae374afb2",
    "type": "split",
    "children": [
      {
        "id": "af8f50da7c4c47b4",
        "type": "tabs",
        "children": [
          {
            "id": "f6021eed9a01763e",
            "type": "leaf",
            "state": {
              "type": "markdown",
              "state": {
                "file": "Zettelkasten/Producer-Consumer Problem.md",
                "mode": "source",
                "source": false
              },
              "icon": "lucide-file",
              "title": "Producer-Consumer Problem"
            }
          },
          {
            "id": "44e7d58a67bba2b7",
            "type": "leaf",
            "state": {
              "type": "markdown",
              "state": {
                "file": "Zettelkasten/State Diagram.md",
                "mode": "source",
                "source": false
              },
              "icon": "lucide-file",
              "title": "State Diagram"
            }
          },
          {
            "id": "997598ee356ab049",
            "type": "leaf",
            "state": {
              "type": "markdown",
              "state": {
                "file": "Zettelkasten/Design Thinking.md",
                "mode": "source",
                "source": false
              },
              "icon": "lucide-file",
              "title": "Design Thinking"
            }
          },
          {
            "id": "ed1551cdf230b24f",
            "type": "leaf",
            "state": {
              "type": "markdown",
              "state": {
                "file": "Templates/Core Zettel Idea.md",
                "mode": "source",
                "source": false
              },
              "icon": "lucide-file",
              "title": "Core Zettel Idea"
            }
          },
          {
            "id": "9158b72329b862f4",
            "type": "leaf",
            "state": {
              "type": "markdown",
              "state": {
                "file": "Zettelkasten/Process.md",
                "mode": "source",
                "source": false
              },
              "icon": "lucide-file",
              "title": "Process"
            }
          },
          {
            "id": "5fd6b1605a3de043",
            "type": "leaf",
            "state": {
              "type": "markdown",
              "state": {
                "file": "Zettelkasten/Be Fully Honest, Stature Be Damned.md",
                "mode": "source",
                "source": false
              },
              "icon": "lucide-file",
              "title": "Be Fully Honest, Stature Be Damned"
            }
          },
          {
            "id": "fe17205af3fbb19b",
            "type": "leaf",
            "state": {
              "type": "markdown",
              "state": {
                "file": "Zettelkasten/Follow Your Curiosity.md",
                "mode": "source",
                "source": false
              },
              "icon": "lucide-file",
              "title": "Follow Your Curiosity"
            }
          },
          {
            "id": "43d457240ef95c77",
            "type": "leaf",
            "state": {
              "type": "markdown",
              "state": {
                "file": "Zettelkasten/Seek Understanding, Not Memorization.md",
                "mode": "source",
                "source": false
              },
              "icon": "lucide-file",
              "title": "Seek Understanding, Not Memorization"
            }
          }
        ],
        "currentTab": 7
      }
    ],
    "direction": "vertical"
  },
  "left": {
    "id": "94fcd40ca2b4fdfb",
    "type": "split",
    "children": [
      {
        "id": "bd6d7e08fefe3188",
        "type": "tabs",
        "children": [
          {
            "id": "f625075916d92821",
            "type": "leaf",
            "state": {
              "type": "file-explorer",
              "state": {
                "sortOrder": "alphabetical",
                "autoReveal": false
              },
              "icon": "lucide-folder-closed",
              "title": "Files"
            }
          },
          {
            "id": "e63c6efaab1c54c1",
            "type": "leaf",
            "state": {
              "type": "search",
              "state": {
                "query": "tag:#idea",
                "matchingCase": false,
                "explainSearch": false,
                "collapseAll": false,
                "extraContext": false,
                "sortOrder": "alphabetical"
              },
              "icon": "lucide-search",
              "title": "Search"
            }
          },
          {
            "id": "b153733ddbaac68a",
            "type": "leaf",
            "state": {
              "type": "bookmarks",
              "state": {},
              "icon": "lucide-bookmark",
              "title": "Bookmarks"
            }
          }
        ],
        "currentTab": 1
      }
    ],
    "direction": "horizontal",
    "width": 200,
    "collapsed": true
  },
  "right": {
    "id": "2d8cf16d06c3ef6e",
    "type": "split",
    "children": [
      {
        "id": "44fda12660d6c152",
        "type": "tabs",
        "children": [
          {
            "id": "fea3245e39cc5788",
            "type": "leaf",
            "state": {
              "type": "backlink",
              "state": {
                "file": "Zettelkasten/The Uses of Not.md",
                "collapseAll": false,
                "extraContext": true,
                "sortOrder": "alphabetical",
                "showSearch": false,
                "searchQuery": "",
                "backlinkCollapsed": false,
                "unlinkedCollapsed": false
              },
              "icon": "links-coming-in",
              "title": "Backlinks for The Uses of Not"
            }
          },
          {
            "id": "73eecb7056482205",
            "type": "leaf",
            "state": {
              "type": "outgoing-link",
              "state": {
                "file": "Zettelkasten/Heuristics.md",
                "linksCollapsed": false,
                "unlinkedCollapsed": true
              },
              "icon": "links-going-out",
              "title": "Outgoing links from Heuristics"
            }
          },
          {
            "id": "7dbcec5c44a0098b",
            "type": "leaf",
            "state": {
              "type": "tag",
              "state": {
                "sortOrder": "frequency",
                "useHierarchy": true
              },
              "icon": "lucide-tags",
              "title": "Tags"
            }
          },
          {
            "id": "fbf306f40df085e9",
            "type": "leaf",
            "state": {
              "type": "outline",
              "state": {
                "file": "Zettelkasten/DC's problems in Regulating AI.md"
              },
              "icon": "lucide-list",
              "title": "Outline of DC's problems in Regulating AI"
            }
          },
          {
            "id": "cb1fd3b345e70ff0",
            "type": "leaf",
            "state": {
              "type": "calendar",
              "state": {},
              "icon": "calendar-with-checkmark",
              "title": "Calendar"
            }
          }
        ],
        "currentTab": 1
      }
    ],
    "direction": "horizontal",
    "width": 200,
    "collapsed": true
  },
  "left-ribbon": {
    "hiddenItems": {
      "switcher:Open quick switcher": false,
      "graph:Open graph view": false,
      "canvas:Create new canvas": false,
      "daily-notes:Open today's daily note": false,
      "templates:Insert template": false,
      "command-palette:Open command palette": false
    }
  },
  "active": "43d457240ef95c77",
  "lastOpenFiles": [
    "Zettelkasten/Follow Your Curiosity.md",
    "Zettelkasten/Seek Understanding, Not Memorization.md",
    "Zettelkasten/Be Fully Honest, Stature Be Damned.md",
    "Zettelkasten/State Diagram.md",
    "Zettelkasten/Use a Different Set of Tools.md",
    "Zettelkasten/Extreme Programming (XP).md",
    "Zettelkasten/CRUDs.md",
    "Zettelkasten/Compare & Swap.md",
    "Zettelkasten/Design Thinking.md",
    "Zettelkasten/Learned Helplessness.md",
    "Zettelkasten/Fragmentation.md",
    "Zettelkasten/Scrum.md",
    "Zettelkasten/Semaphores.md",
    "Zettelkasten/Mutual Exclusion with CAS.md",
    "Zettelkasten/Mutex Locks.md",
    "Zettelkasten/Untitled 1.md",
    "Zettelkasten/Producer-Consumer Problem.md",
    "Templates/Core Zettel Idea.md",
    "Zettelkasten/Critical-Section.md",
    "Zettelkasten/Process.md",
    "Zettelkasten/Synchronization Tools.md",
    "Zettelkasten/Heuristics.md",
    "Zettelkasten/Heuristics & Biases.md",
    "Zettelkasten/Typescript.md",
    "Zettelkasten/Dust of The Way (Q).md",
    "Zettelkasten/UI, UX.md",
    "Untitled.canvas",
    "Files/120283771_CLAYPOT1_1495890635.jpg",
    "Files/Pasted image.png",
    "Files/Screenshot From 2025-05-07 06-33-19.png",
    "Files/Screenshot From 2025-05-07 03-02-16.png",
    "Files/Screenshot From 2025-05-07 03-01-05.png",
    "Files/Pasted image 20250422201653.png",
    "Files/Screenshot 2025-04-22 195747.png",
    "Files/Screenshot 2025-04-22 192912.png",
    "Files/mermaid-diagram-2025-04-22-173048.png",
    "Files/mermaid-diagram-2025-04-22-173048.png.crdownload",
    "Files/Screenshot 2025-04-22 165017.png",
    "Files/mermaid-diagram-2025-04-22-161031.png.crdownload",
    "Files/fp&fcp.png.crdownload",
    "Files/whatis-waterfall_model_mobile.png.crdownload",
    "Files/Unconfirmed 779050.crdownload",
    "Files/mermaid-diagram-2025-04-10-211542.png.crdownload",
    "Files/semantic versioning.png.crdownload",
    "Files/4.png.crdownload",
    "Files/inner-outer-alignment-person-diagram-2.png.crdownload",
    "Files/1-s2.0-S0016328721001932-gr2.jpg.crdownload",
    "demos/Canvas-demo.canvas",
    "Untitled 1.canvas"
  ]
}